{"error":"OK","limit":1,"offset":0,"number_of_page_results":1,"number_of_total_results":1,"status_code":1,"results":{"air_date":null,"aliases":null,"api_detail_url":"https://comicvine.gamespot.com/api/episode/4070-93/","character_credits":[{"api_detail_url":"https://comicvine.gamespot.com/api/character/4005-18419/","id":18419,"name":"Mulder","site_detail_url":"https://comicvine.gamespot.com/mulder/4005-18419/"},{"api_detail_url":"https://comicvine.gamespot.com/api/character/4005-18420/","id":18420,"name":"Scully","site_detail_url":"https://comicvine.gamespot.com/scully/4005-18420/"}],"character_died_in":[],"concept_credits":[],"date_added":"2013-09-24 14:28:43","date_last_updated":"2013-10-05 18:24:04","deck":"The employees of a chicken processing factory exhibit increasingly bizarre symptoms and behaviour.","description":null,"episode_number":"224","first_appearance_characters":null,"first_appearance_concepts":null,"first_appearance_locations":null,"first_appearance_objects":null,"first_appearance_storyarcs":null,"first_appearance_teams":null,"has_staff_review":false,"id":93,"image":{"icon_url":"https://comicvine.gamespot.com/a/uploads/square_avatar/13/132162/3332298-screenshot01.jpg","medium_url":"https://comicvine.gamespot.com/a/uploads/scale_medium/13/132162/3332298-screenshot01.jpg","screen_url":"https://comicvine.gamespot.com/a/uploads/screen_medium/13/132162/3332298-screenshot01.jpg","screen_large_url":"https://comicvine.gamespot.com/a/uploads/screen_kubrick/13/132162/3332298-screenshot01.jpg","small_url":"https://comicvine.gamespot.com/a/uploads/scale_small/13/132162/3332298-screenshot01.jpg","super_url":"https://comicvine.gamespot.com/a/uploads/scale_large/13/132162/3332298-screenshot01.jpg","thumb_url":"https://comicvine.gamespot.com/a/uploads/scale_avatar/13/132162/3332298-screenshot01.jpg","tiny_url":"https://comicvine.gamespot.com/a/uploads/square_mini/13/132162/3332298-screenshot01.jpg","original_url":"https://comicvine.gamespot.com/a/uploads/original/13/132162/3332298-screenshot01.jpg","image_tags":"All Images"},"location_credits":[],"name":"Our Town","object_credits":[],"series":{"api_detail_url":"https://comicvine.gamespot.com/api/series/4075-8/","id":8,"name":"The X-Files","site_detail_url":"https://comicvine.gamespot.com/the-xfiles/4075-8/"},"site_detail_url":"https://comicvine.gamespot.com/the-x-files-224-our-town/4070-93/","story_arc_credits":[],"team_credits":[{"api_detail_url":"https://comicvine.gamespot.com/api/team/4060-55443/","id":55443,"name":"Federal Bureau of Investigation","site_detail_url":"https://comicvine.gamespot.com/federal-bureau-of-investigation/4060-55443/"},{"api_detail_url":"https://comicvine.gamespot.com/api/team/4060-46347/","id":46347,"name":"X-Files","site_detail_url":"https://comicvine.gamespot.com/x-files/4060-46347/"}]},"version":"1.0"}